sklearn_numba_dpex/__init__.py
sklearn_numba_dpex-0.1.0.dev0.dist-info/LICENSE.txt
sklearn_numba_dpex-0.1.0.dev0.dist-info/METADATA
sklearn_numba_dpex-0.1.0.dev0.dist-info/WHEEL
sklearn_numba_dpex-0.1.0.dev0.dist-info/entry_points.txt
sklearn_numba_dpex-0.1.0.dev0.dist-info/top_level.txt
sklearn_numba_dpex-0.1.0.dev0.dist-info/RECORD
