Metadata-Version: 2.1
Name: sklearn-numba-dpex
Version: 0.1.0.dev0
Summary: Computational Engine for scikit-learn based on numba-dpex
Maintainer-email: Olivier Grisel <olivier.grisel@ensta.org>
License: BSD 3-Clause License        
Project-URL: Homepage, https://github.com/ogrisel/sklearn-numba-dpex
Classifier: Intended Audience :: Science/Research
Classifier: Intended Audience :: Developers
Classifier: License :: OSI Approved
Classifier: Programming Language :: Python
Classifier: Topic :: Software Development
Classifier: Topic :: Scientific/Engineering
Classifier: Development Status :: 4 - Beta
Classifier: Operating System :: Microsoft :: Windows
Classifier: Operating System :: POSIX
Classifier: Operating System :: Unix
Classifier: Operating System :: MacOS
Classifier: Programming Language :: Python :: 3
Classifier: Programming Language :: Python :: 3.8
Classifier: Programming Language :: Python :: 3.9
Classifier: Programming Language :: Python :: 3.10
Classifier: Programming Language :: Python :: Implementation :: CPython
Requires-Python: >=3.8
License-File: LICENSE.txt
Requires-Dist: scikit-learn
Requires-Dist: numba-dpex
Requires-Dist: dpctl
Requires-Dist: pyopencl
Provides-Extra: benchmark
Requires-Dist: scikit-learn-intelex ; extra == 'benchmark'
Requires-Dist: pandas ; extra == 'benchmark'
